philately/__init__.py
philately/analyze_collection.py
philately/llm_caller.py
philately/main.py
philately/philately_objects.py
philately/philately_ui.py
philately/processor_v2.py
philately_will_get_you_everywhere-0.1.0.dist-info/licenses/LICENSE
philately_will_get_you_everywhere-0.1.0.dist-info/METADATA
philately_will_get_you_everywhere-0.1.0.dist-info/WHEEL
philately_will_get_you_everywhere-0.1.0.dist-info/entry_points.txt
philately_will_get_you_everywhere-0.1.0.dist-info/top_level.txt
philately_will_get_you_everywhere-0.1.0.dist-info/RECORD
