Metadata-Version: 2.4
Name: philately-will-get-you-everywhere
Version: 0.1.0
Summary: A Python-based command-line system for managing a philatelic (stamp) collection.
Author-email: Fred Zimmerman <fred.zimmerman@gmail.com>
License: MIT
Classifier: Development Status :: 4 - Beta
Classifier: Intended Audience :: Developers
Classifier: License :: OSI Approved :: MIT License
Classifier: Programming Language :: Python :: 3
Classifier: Programming Language :: Python :: 3.13
Requires-Python: >=3.12
License-File: LICENSE
Requires-Dist: google-generativeai>=0.8.5
Requires-Dist: markdown>=3.8
Requires-Dist: openai>=1.84.0
Requires-Dist: opencv-python>=4.11.0.86
Requires-Dist: pdflatex>=0.1.3
Requires-Dist: pymupdf>=1.26.0
Requires-Dist: python-dotenv>=1.1.0
Requires-Dist: streamlit>=1.45.1
Requires-Dist: litellm>=1.35.2
Requires-Dist: pandas>=2.2.0
Requires-Dist: tqdm>=4.66.1
Dynamic: license-file
